eseq/__init__.py
eseq/bio_dna.py
eseq/dna.py
eseq/orf.py
eseq/palindromic.py
eseq/prosite.py
eseq/protein.py
eseq/rna.py
eseq/seq.py
eseq/trim_seq.py
eseq/model/__init__.py
eseq/model/compress.py
eseq/model/scan.py
eseq/model/seq_trie.py
eseq/utils/constants.py
eseq-0.0.4.dist-info/LICENSE
eseq-0.0.4.dist-info/METADATA
eseq-0.0.4.dist-info/WHEEL
eseq-0.0.4.dist-info/top_level.txt
eseq-0.0.4.dist-info/RECORD
