Metadata-Version: 2.1
Name: eseq
Version: 0.0.4
Summary: Process genomic sequences.
Home-page: https://github.com/Tiezhengyuan/bio_sequence.git
Author: Tiezheng Yuan
Author-email: tiezhengyuan@hotmail.com
Keywords: pypi,cicd,python
Classifier: Development Status :: 1 - Planning
Classifier: Intended Audience :: Developers
Classifier: Programming Language :: Python :: 3
Classifier: Operating System :: Unix
Classifier: Operating System :: MacOS :: MacOS X
Classifier: Operating System :: Microsoft :: Windows
License-File: LICENSE
Requires-Dist: Bio
